pandass/__init__.py
pandass/project.py
pandass/single_words.py
pandass/words2.py
pandass-1.11.4.dist-info/LICENSE.txt
pandass-1.11.4.dist-info/METADATA
pandass-1.11.4.dist-info/WHEEL
pandass-1.11.4.dist-info/top_level.txt
pandass-1.11.4.dist-info/RECORD
