Metadata-Version: 2.1
Name: pandass
Version: 1.11.4
Summary: This is a simple example package
Home-page: https://github.com/pypa/sampleproject
Author: Aditya Kumar
Author-email: Adityakumarec@gmail.com
License: UNKNOWN
Platform: UNKNOWN
Classifier: Programming Language :: Python :: 3
Classifier: License :: OSI Approved :: MIT License
Classifier: Operating System :: OS Independent
Requires-Python: >=3.6
